qa_agent.py
qa_agent_cli-1.0.0.dist-info/licenses/LICENSE
qa_agent_cli-1.0.0.dist-info/METADATA
qa_agent_cli-1.0.0.dist-info/WHEEL
qa_agent_cli-1.0.0.dist-info/entry_points.txt
qa_agent_cli-1.0.0.dist-info/top_level.txt
qa_agent_cli-1.0.0.dist-info/RECORD
