Metadata-Version: 2.4
Name: qa-agent-cli
Version: 1.0.0
Summary: AI-powered code quality analysis tool using Groq Llama
Author: QA Agent Team
Author-email: Your Name <your.email@example.com>
License: MIT
Project-URL: Homepage, https://github.com/yourusername/qa-agent-cli
Project-URL: Repository, https://github.com/yourusername/qa-agent-cli
Keywords: code-quality,ai,linting,security,groq,llama
Classifier: Development Status :: 4 - Beta
Classifier: Intended Audience :: Developers
Classifier: License :: OSI Approved :: MIT License
Classifier: Programming Language :: Python :: 3.9
Classifier: Programming Language :: Python :: 3.10
Classifier: Programming Language :: Python :: 3.11
Classifier: Programming Language :: Python :: 3.12
Classifier: Topic :: Software Development :: Quality Assurance
Requires-Python: >=3.9
License-File: LICENSE
Requires-Dist: groq>=0.4.0
Requires-Dist: click>=8.1.0
Requires-Dist: rich>=13.0.0
Requires-Dist: reportlab>=4.0.0
Requires-Dist: python-dotenv>=1.0.0
Dynamic: author
Dynamic: license-file
Dynamic: requires-python
